najrono/__init__.py
najrono/fields.py
najrono/main.py
najrono/mixin.py
najrono/utils.py
najrono-0.0.8.dist-info/licenses/LICENSE
najrono-0.0.8.dist-info/METADATA
najrono-0.0.8.dist-info/WHEEL
najrono-0.0.8.dist-info/top_level.txt
najrono-0.0.8.dist-info/RECORD
