Metadata-Version: 2.4
Name: najrono
Version: 0.0.8
Summary: Django library for managing **Jalali (Persian) dates** in your models
Home-page: https://github.com/tahamusvi/najrono
Author: Taha Musvi
Author-email: TahaM8000@gmail.com
Classifier: Programming Language :: Python :: 3
Classifier: License :: OSI Approved :: MIT License
Classifier: Operating System :: OS Independent
Requires-Python: >=3.6
License-File: LICENSE
Requires-Dist: jalali_core==1.0.0
Requires-Dist: jdatetime==5.0.0
Requires-Dist: django==4.2.16
Dynamic: author
Dynamic: author-email
Dynamic: classifier
Dynamic: description
Dynamic: description-content-type
Dynamic: home-page
Dynamic: license-file
Dynamic: requires-dist
Dynamic: requires-python
Dynamic: summary
